is_online/__init__.py
is_online/__main__.py
is_online-1.0.2.dist-info/METADATA
is_online-1.0.2.dist-info/WHEEL
is_online-1.0.2.dist-info/entry_points.txt
is_online-1.0.2.dist-info/top_level.txt
is_online-1.0.2.dist-info/RECORD
