Metadata-Version: 2.1
Name: is-online
Version: 1.0.2
Summary: A Python module meant for cli use which checks whether you are connected to the Internet.
Home-page: https://github.com/glenncalleja/is_online
Author: Glenn Calleja Frendo
Author-email: glenncal@gmail.com
License: UNKNOWN
Platform: UNKNOWN
Classifier: Programming Language :: Python :: 3
Classifier: License :: OSI Approved :: MIT License
Classifier: Operating System :: OS Independent
Requires-Python: >=3.6
